[
  {
    "id": "prod_running_shoes_142",
    "parent_asin": "B09MNM6GM2",
    "category": "Running Shoes",
    "title": "XIANV Women Men Running Shoes Breathable Slip On Sneakers Mesh Sport Athletic Fashion Tennis Comfort Fitness Walking Shoes",
    "description": "",
    "rating": 4.2,
    "review_count": 724,
    "features": [
      "Rubber sole"
    ],
    "reviews": [
      {
        "rating": 3.0,
        "title": "8.5 was a 41? It should be 42",
        "text": "Ordered a us 8.5 and a 41 was delivered. Every other 8.5 I have ordered has said 42 as the size. This caused my toes rub and touch the ends of the shoe. I believe sizing is wrong. Has just for fun new fashion printed on the sides which make the shoes loook really cheap. Bottom green portion not as dark as product pictures bust is acceptable. Order half a size larger then normal.",
        "verified": true,
        "helpful_votes": 1
      },
      {
        "rating": 4.0,
        "title": "A good pair of shoes",
        "text": "Bought for running but they are not performing well. They are too stiff. You get you what you pay for. So no complaints. They are surprisingly stylish. I wear them everyday.",
        "verified": true,
        "helpful_votes": 1
      },
      {
        "rating": 5.0,
        "title": "Exactly as described",
        "text": "Fits well.  Very nice product.  Love the colors.",
        "verified": true,
        "helpful_votes": 0
      },
      {
        "rating": 5.0,
        "title": "Worth it.",
        "text": "Comfortable right out of box. No breaking in. Love them.",
        "verified": true,
        "helpful_votes": 0
      },
      {
        "rating": 4.0,
        "title": "Bien",
        "text": "Las trenzas o cordones podr\u00edan ser de mejor calidad aunque cumplen la tarea.",
        "verified": true,
        "helpful_votes": 0
      }
    ],
    "store": "XIANV",
    "tags": [],
    "price": 16.99,
    "position": 1,
    "page": 1
  },
  {
    "id": "prod_running_shoes_193",
    "parent_asin": "B07MXP5TKR",
    "category": "Running Shoes",
    "title": "ASICS Men's Gel-Contend 5 Running Shoes",
    "description": "Go further than ever before with the GEL-CONTEND 5 extra wide width men's running shoe from ASICS. Created to offer the stability required to help you go the distance this shoe offers a supportive fit thanks to an internal heel counter. Features include a removable sockliner Rearfoot GEL technology and an AMPLIFOAM midsole which ensure your foot remains cushioned every step of the way. The solid rubber outsole and stitch-down toe reinforcement also mean it has a high level of durability while the breathable athletic mesh means that your feet stay fresher for longer as you take on new challenges. Proudly sporting our classic logo on the side you can rest assured that the GEL-CONTEND 5 shoe will give you comfort and protection when you need it most. Weight: 10.25. Heel Height: 22mm. Forefoot Height: 12mm.",
    "rating": 4.6,
    "review_count": 11049,
    "features": [],
    "reviews": [
      {
        "rating": 5.0,
        "title": "Order 1 size larger",
        "text": "Fits great just like the old asics. Remember to order 1 size larger",
        "verified": true,
        "helpful_votes": 0
      },
      {
        "rating": 5.0,
        "title": "Fit and price.",
        "text": "I have bought these twice before. I like the fit and I use them for daily use and running around. That\u2019s why I didn\u2019t rate them for working out. I use the ASICS 7 for power walking.",
        "verified": true,
        "helpful_votes": 0
      },
      {
        "rating": 4.0,
        "title": "Very comfortable",
        "text": "Not the best looking shoe, but very comfortable",
        "verified": true,
        "helpful_votes": 0
      },
      {
        "rating": 5.0,
        "title": "Very comfortable shoe",
        "text": "Very comfortable, nice fit.  We live in a cold climate so I bought these a half size larger to fit with thicker socks and that is perfect!",
        "verified": true,
        "helpful_votes": 0
      },
      {
        "rating": 5.0,
        "title": "?",
        "text": "GOOD FIT.  USED WALKING.  PLAN TO RUN IN THEM",
        "verified": true,
        "helpful_votes": 0
      }
    ],
    "store": "ASICS",
    "tags": [
      "Sponsored"
    ],
    "price": 89.95,
    "position": 2,
    "page": 1
  },
  {
    "id": "prod_running_shoes_076",
    "parent_asin": "B09MMTVR7S",
    "category": "Running Shoes",
    "title": "PUMA Men's Softride Rift Slip on Running Shoe",
    "description": "The SOFTRIDE Rift is PUMA\u2019s first introduction into the SOFTRIDE franchise. With full length SOFTRIDE in the midsole, this style keeps you light on your feet for an all day cushioned feel. This upper features a true slip on bootie construction and is highlighted by a Bold PUMA lateral branding,.? ? The SOFTRIDE Rift provide extreme cushioning and all-day comfort without sacrificing the casual look that you crave. Look Good Feel Good. ? ? ?",
    "rating": 4.4,
    "review_count": 8,
    "features": [
      "Rubber sole",
      "Featuring Softride Slip On",
      "Knitted Upper",
      "PUMA Foamstrip Overlays At Side",
      "Slip-On Design",
      "Webbing Pull-Loops At Heel And Tongue"
    ],
    "reviews": [
      {
        "rating": 3.0,
        "title": "Squeakers!",
        "text": "These were super comfortable. But they squeak on tile and other hard, smooth surfaces. They could hear me 100 plus yard away at the hospital I work at.",
        "verified": false,
        "helpful_votes": 0
      }
    ],
    "store": "PUMA",
    "tags": [],
    "price": 119.0,
    "position": 3,
    "page": 1
  },
  {
    "id": "prod_running_shoes_041",
    "parent_asin": "B07HQX118J",
    "category": "Running Shoes",
    "title": "Nike Women's Odyssey React Flyknit 2 Running Shoes Teal Tint and Sail 8.5",
    "description": "",
    "rating": 4.1,
    "review_count": 13,
    "features": [
      "Rubber sole"
    ],
    "reviews": [
      {
        "rating": 5.0,
        "title": "Comfortable",
        "text": "Sneakers are super light and comfortable. Perfect for running, walking or jumping rope; I have plantar fasciitis and I don't feel pain when wearing these.",
        "verified": true,
        "helpful_votes": 0
      }
    ],
    "store": "Nike",
    "tags": [],
    "price": 85.0,
    "position": 4,
    "page": 1
  },
  {
    "id": "prod_running_shoes_021",
    "parent_asin": "B01M25J3CB",
    "category": "Running Shoes",
    "title": "Klitch Footwear Clip Sports Accessory, Hang Extra Shoes Cleats Boots or Gear on Your Bag. Works on Soccer, Baseball, Basketball, Track, Running Shoes, Flip Flops and More.",
    "description": "The Klitch is a footwear clip that allows you to hang extra sneakers or cleats to the outside of your bag. This avoids getting the inside of your bag dirty, smelly, and full. Great for anyone who plays sports, works out, or has an active lifestyle. The Klitch can be used for any type of footwear up to 10 lbs!",
    "rating": 4.5,
    "review_count": 1299,
    "features": [
      "PATENTED: The Klitch Footwear Clip allows you to carry extra shoes outside your bag allowing your shoes to air out and the contents of your bag to stay clean and fresh!",
      "QUICK & EASY: No more messy and difficult knots to tie or untie. Quickly and easily clamp and clip extra shoes or equipment to your bag with no fuss!",
      "PERFECT FOR SPORTS: Great for soccer cleats, football cleats, baseball spikes, basketball shoes, track shoes, hiking boots, flip-flops and much more!",
      "ON THE GO: Great for traveling, hiking, camping or organizing at home. Hang extra shoes or equipment in your garage, lockers, tents or shoe racks!",
      "CUSTOMER FIRST: The Klitch Footwear Clip includes a 1-year full replacement when purchased through Klitch!"
    ],
    "reviews": [
      {
        "rating": 5.0,
        "title": "Great for Volleyball Shoes",
        "text": "Absolutly love it ... hold volleyball shoes on the outside of the bag ... if there was an update to the design it would be to make a clip open wide enough so shoes could go heel to heel to keep dirt or elements together.<br /><br />If you looking for a clip to hold shoes on the outside of the bag -- Look No Further - THIS IS IT!",
        "verified": true,
        "helpful_votes": 2
      },
      {
        "rating": 5.0,
        "title": "Does it\u2019s job",
        "text": "This product does the job. No frills but does what it\u2019s designed to do. The clip gets a little hard to open but o actually like it because running throw the airport with muddy sneakers o never worry about them coming loose",
        "verified": true,
        "helpful_votes": 1
      },
      {
        "rating": 1.0,
        "title": "Not worth 20 or even 15",
        "text": "Good idea, but the metal clip fell of within 20 uses. This item just isn't made with quality in mind, wish it was!",
        "verified": true,
        "helpful_votes": 1
      },
      {
        "rating": 3.0,
        "title": "Great while it lasted!",
        "text": "Worked great for about 5 months.",
        "verified": false,
        "helpful_votes": 0
      },
      {
        "rating": 1.0,
        "title": "Cheap junk",
        "text": "The plastic broke after using it 5 or 6 times. Avoid.",
        "verified": false,
        "helpful_votes": 0
      }
    ],
    "store": "Klitch",
    "tags": [],
    "price": 19.49,
    "position": 5,
    "page": 1
  },
  {
    "id": "prod_running_shoes_107",
    "parent_asin": "B086V6MC7B",
    "category": "Running Shoes",
    "title": "LUCKY STEP Women's Leopard Colorblock lace up Sneakers Cosy Chunky Climbing Hiking Running Shoes.",
    "description": "",
    "rating": 3.7,
    "review_count": 1453,
    "features": [
      "Imported",
      "Rubber sole",
      "Material : PU+ PVC out sole",
      "Measurement: Heel Height about 5.5cm,Width about 9.5 cm,true to size",
      "Suitable for all women to wear in various scenes,walking, running, shopping, dating,go to school etc.",
      "Color clash design makes the shoes fashion ,the Leopard print is a popular element at the moment.",
      "Durable,Cosy and animal-friendly,this style features man-made materials throughout."
    ],
    "reviews": [
      {
        "rating": 2.0,
        "title": "Uncomfortable and run a bit small",
        "text": "Very cute but so uncomfortable.",
        "verified": true,
        "helpful_votes": 0
      },
      {
        "rating": 5.0,
        "title": "very nice comfortable shoe",
        "text": "I like the looks and feel of these shoes",
        "verified": true,
        "helpful_votes": 0
      },
      {
        "rating": 1.0,
        "title": "Very uncomfortable! Don't buy these shoes",
        "text": "Very uncomfortable top area of the show. Cheap made shoe. Poor quality. It was stiff and pinched my upper foot area where the shoe ties were. Not  comfortable...not worth the price!",
        "verified": true,
        "helpful_votes": 0
      },
      {
        "rating": 5.0,
        "title": "Stylish and comfortable with a little wedge",
        "text": "Cute shoes! I ordered a 1/2 size up based on the reviews, but I would recommend ordering your regular size as I found the shoes run wide and as expected.",
        "verified": true,
        "helpful_votes": 0
      }
    ],
    "store": "LUCKY STEP",
    "tags": [],
    "price": 30.99,
    "position": 6,
    "page": 1
  },
  {
    "id": "prod_running_shoes_010",
    "parent_asin": "B09SHFJXV5",
    "category": "Running Shoes",
    "title": "AUGSUN 110pcs 1/4inch Stainless Steel Track and Cross Country Spikes with Spike Wrench, Replacement Spikes for Sprint Sports Short Running Shoes\u2026",
    "description": "",
    "rating": 4.6,
    "review_count": 818,
    "features": [
      "stainless steel",
      "\u3010QUALITY MATERIAL\u3011: Made of quality stainless steel, which is very sturdy, rust-resist and anti-corrode. Pyramid needle design, not damage track. Very practical items for both men and women.",
      "\u3010PACKAGE INCLUDES\u3011: Package includes 110 pieces spikes with 1pcs spike wrench, convenient for you to replace your shoe spikes. There are enough quantity for your daily use.",
      "\u3010SIZE\u3011: 6.35 mm (1/4 inch) in length, tapered and needle-shaped, which increases friction between the sole and the ground and prevents skidding.",
      "\u3010EASY TO USE & REPLACE SPIKES\u3011: The package includes a spike wrench. It is very easy for you to screw the track spikes into the shoes, convenient to replace the spikes. Ideal for athletic tracks, field and cross country surfaces.",
      "\u3010PROVIDE GREAT DRIP FOR SPORTSMAN\u3011: The spike pins can increase the friction between the shoe sole and ground, resist skid and improve your running balance of traction, flexibility and speed for track sprints, long jump, running."
    ],
    "reviews": [
      {
        "rating": 2.0,
        "title": "Cheap price, cheap product",
        "text": "Lots of the spikes I received were malformed. They were too round to fit the wrench key that came with them so I couldn't screw them in. At least one of them is stuck and I am unsure if I will be able to remove it.<br /><br />I would suggest going with something else.",
        "verified": true,
        "helpful_votes": 3
      },
      {
        "rating": 5.0,
        "title": "Works well",
        "text": "these work well and have yet to find one that had a defect even the tool it came with is made strong",
        "verified": true,
        "helpful_votes": 1
      },
      {
        "rating": 4.0,
        "title": "Great value...",
        "text": "My teenager says they fit, are durable and easy to install.",
        "verified": true,
        "helpful_votes": 0
      },
      {
        "rating": 5.0,
        "title": "Good buy",
        "text": "Works well. Good price.",
        "verified": true,
        "helpful_votes": 0
      },
      {
        "rating": 5.0,
        "title": "Good quality",
        "text": "Arrive fast and you get a lot for your money!",
        "verified": true,
        "helpful_votes": 0
      }
    ],
    "store": "AUGSUN",
    "tags": [],
    "price": 9.95,
    "position": 7,
    "page": 1
  },
  {
    "id": "prod_running_shoes_069",
    "parent_asin": "B07QY9WXQQ",
    "category": "Running Shoes",
    "title": "ASICS Men's Gel-Kayano 26 Running Shoes",
    "description": "Celebrate the retro style of the historic Japanese capital in this special edition GEL-KAYANO 26 Retro Tokyo running shoe from ASICS. This updated version combines advanced components with a striking new design that honors Tokyo's heritage. The GEL-KAYANO 26 shoe allows you to tackle long distances in comfort, thanks to the rearfoot GEL technology that's been redesigned for improved shock absorption upon impact. You'll also benefit from a bouncy feel that stems from the FLYTEFOAM Propel midsole technology. The DUOMAX technology in the midsole offers better support and helps resist excessive overpronation while I.G.S. technology promotes smoother propulsion. Additionally, this style is accented with reflective detailing to improve your visibility when running in low light settings. Get the inspiration and support you need to smash your training goals in the special edition GEL-KAYANO 26 Retro Tokyo performance running shoe from ASICS.",
    "rating": 4.7,
    "review_count": 7780,
    "features": [
      "Synthetic-and-mesh"
    ],
    "reviews": [
      {
        "rating": 1.0,
        "title": "ASICS Men's Gel-Kayano 26 doesn't work for me",
        "text": "I really wanted to love these shoes. I bought the Black ones and they looked great. But trying them on was another thing. Under where my toes connect to my feet there is a ridge or slight raised part that I could really feel. From the ridge to the toe of the shoe my toes seemed to slightly drop making the shoe very uncomfortable for me.<br />I am really glad that I purchased them through Amazon the free return policy worked for me. I sent the shoes back the next morning. The credit showed up the next morning.",
        "verified": true,
        "helpful_votes": 6
      },
      {
        "rating": 5.0,
        "title": "Super shoes\u2014 my 6th pair!",
        "text": "I get a new pair every year for birthday and absolutely LOVE them ! Great fit, fine look, they seem to get better every year!!!",
        "verified": true,
        "helpful_votes": 0
      },
      {
        "rating": 5.0,
        "title": "Asics Kayano",
        "text": "Asics Kayano's are the best!  Lots of support in the heel, and the Duomax support system is awesome!",
        "verified": true,
        "helpful_votes": 0
      },
      {
        "rating": 5.0,
        "title": "Update:Tread showing considerable wear after 70 miles",
        "text": "Two star: Upper is holding up nicely. Tread is already worn out after only 70 miles. I tried ASICS because reviews talk of superior durability. So far for me  upper is good, sole is not.<br /><br />Update: I reached out to ASICS about the tread life. After sending pictures of tread wear after 70 miles they sent code for replacement shoe from ASICS.com.<br />That\u2019s pretty awesome customer service in my book.<br /><br />So far 20 miles on new Kayano fit and finish is great.<br /><br />Comfort on gel-Kayano 28 is far superior to previous models.<br /><br />Extra wide is a touch narrow but all in all the first 20 miles is running great.",
        "verified": true,
        "helpful_votes": 0
      },
      {
        "rating": 5.0,
        "title": "He\u2019ll only wear ASICS",
        "text": "My husband buys one pair of shoes a year (imagine that!). Of course, he wears them every single day\u2014365 days! ASICS are the best fit and most comfortable for him. They\u2019re fit true to size and are just as advertised. He\u2019s very happy!",
        "verified": true,
        "helpful_votes": 0
      }
    ],
    "store": "ASICS",
    "tags": [],
    "price": 159.95,
    "position": 8,
    "page": 1
  },
  {
    "id": "prod_running_shoes_075",
    "parent_asin": "B09XZLV44K",
    "category": "Running Shoes",
    "title": "New Balance DRFT Running Shoe White",
    "description": "New Balance DRFT Women's Running Shoe Complete your next exercise wearing the New Balance DRFT Women's Running Shoe! This style has a breathable mesh upper with a cushioned with a supportive lace-up closure and padded collar. The cushioned insole adds padding and support on the go, while the rubber outsole is lightweight and flexible, perfect for every workout. Move smoothly and comfortably wearing the New Balance DRFT Women's Running Shoe! Lace-up closure Breathable mesh upper Cushioned insole Rubber outsole Padded collar White/Black/Purple Imported | New Balance DRFT Running Shoe White",
    "rating": 4.6,
    "review_count": 54,
    "features": [
      "Imported",
      "Rubber sole",
      "Lace-up closure",
      "Breathable mesh upper",
      "Cushioned insole",
      "Rubber outsole",
      "Padded collar"
    ],
    "reviews": [
      {
        "rating": 5.0,
        "title": "Comfortable",
        "text": "Very light and comfy.",
        "verified": true,
        "helpful_votes": 1
      },
      {
        "rating": 5.0,
        "title": "very comfortable",
        "text": "I love New Balance tennis shoes.  They seem to fit my feet so well.  My last pair was well worn out, so I searched on Amazon to find a new pair.  I found these and the price was so good that I ordered them.  They fit perfectly and I love them.  So cozy to wear.",
        "verified": true,
        "helpful_votes": 0
      }
    ],
    "store": "New Balance",
    "tags": [
      "Sponsored"
    ],
    "price": 58.86,
    "position": 9,
    "page": 1
  },
  {
    "id": "prod_running_shoes_024",
    "parent_asin": "B0BVLHSWFQ",
    "category": "Running Shoes",
    "title": "VOCOOL 100 PCS 1/4inch Stainless Steel Track and Cross Country Spikes with Spike Wrench, Pyramid Replacement Track Spikes for Sprint Sports Short Running Shoes, Black/Silver",
    "description": "",
    "rating": 4.6,
    "review_count": 192,
    "features": [
      "\u3010What You Get\u3011: Package includes 100 pieces black spikes with 1pcs spike wrench, convenient for you to replace your shoe spikes. There are enough quantity for your daily use.",
      "\u3010Quality Material\u3011: These spikes are made of quality hard steel, durable and rust-resist and anti-corrode, ensure you to use for a long time.Easy to match with most of the track shoes, improve your running balance of traction, flexibility and speed.",
      "\u3010Easy to Use & Replace Spikes\u3011: The package includes a spike wrench. It is very easy for you to screw the track spikes into the shoes, convenient to replace the spikes. Ideal for athletic tracks, field and cross country surfaces.",
      "\u3010Size\u3011: 6.35 mm (1/4 inch) in length, tapered and needle-shaped, which increases friction between the sole and the ground and prevents skidding,especially suit for track sprints, long jump,running, outdoor sports activities.",
      "\u3010Improve Running\u3011: If you like running, climbing, or you are a sports enthusiast, this track spikes will help you a lot. This pyramid spikes will add the friction between the shoe sole and ground, thus can resist skid and improve your running speed."
    ],
    "reviews": [
      {
        "rating": 5.0,
        "title": "replacement for broken spikes",
        "text": "I play cricket and the spikes under the shoes break frequently. I have bought this brand, i am hoping they would last me for a long time. They screw into the shoes perfectly",
        "verified": true,
        "helpful_votes": 2
      },
      {
        "rating": 5.0,
        "title": "pyramid spikes",
        "text": "love these but the track does not want pyramid, they want needle spikes. not sure what to do with these now.",
        "verified": true,
        "helpful_votes": 0
      },
      {
        "rating": 5.0,
        "title": "A must have in a coach\u2019s bag",
        "text": "Great value",
        "verified": true,
        "helpful_votes": 0
      },
      {
        "rating": 5.0,
        "title": "Quanity",
        "text": "Nice quantity and great fit dor ny daughter nike cletes.",
        "verified": true,
        "helpful_votes": 0
      },
      {
        "rating": 5.0,
        "title": "Bought them again!",
        "text": "We liked the 1st purchase so much that we bought another for the rest of the season.",
        "verified": true,
        "helpful_votes": 0
      }
    ],
    "store": "VOCOOL",
    "tags": [],
    "price": 7.53,
    "position": 10,
    "page": 1
  },
  {
    "id": "prod_running_shoes_153",
    "parent_asin": "B07RGTWS22",
    "category": "Running Shoes",
    "title": "New Balance Men's 410 V6 Trail Running Shoe",
    "description": "Be off-road ready in the New Balance 410v6 men\u2019s trail shoe. Featuring a durable AT Tread rubber outsole, this shoe is fit for any adventure. Made with a sleek upper, ACTEVA midsole technology and a cushioned NB Comfort Insert, the versatile men\u2019s running shoe is designed to keep you comfortable and stylish before, during and after your hike.\nNew Balance, is dedicated to helping athletes achieve their goals. It's been their mission for more than a century. It's why they don't spend money on celebrity endorsements. They spend it on research and development. It's why they don't design products to fit an image. They design them to fit. New Balance is driven to make the finest shoes for the same reason athletes lace them up: to achieve the very best.",
    "rating": 4.5,
    "review_count": 7439,
    "features": [
      "50% Synthetic, 50% Mesh",
      "Imported",
      "Rubber sole",
      "ACTEVA midsole cushioning delivers versatile, flexible support",
      "AT Tread outsole provides versatile traction during both on and off-road activities",
      "Lightweight injection-molded EVA foam midsole provides lightweight cushioning",
      "NB Comfort Insert offers additional cushioning",
      "Synthetic/mesh upper"
    ],
    "reviews": [
      {
        "rating": 1.0,
        "title": "Sizing",
        "text": "Too narrow",
        "verified": true,
        "helpful_votes": 1
      },
      {
        "rating": 2.0,
        "title": "Cheap quality",
        "text": "These are wimpy tennis shoes.  They probably wont' make it a year.  I judge the quality by picking up the shoe and twisting in my hands.  I can easily warp these shoes.  I have some Merrills and I absolutely can't bend them up.",
        "verified": true,
        "helpful_votes": 1
      },
      {
        "rating": 5.0,
        "title": "Not the best looking shoe but the most comfortable!",
        "text": "Man my feet hurt. And because I wear the same shoes everyday all day they break down pretty quickly.  These are perfect.  The color isn't my absolute favorite BUT that was the color that was on sale. Besides I'm nearly 50 so I'm not out to impress anyone lol.  They fit my feet perfectly and  there is no better feeling of new shoes when your old shoes broke down! Just enough support.",
        "verified": true,
        "helpful_votes": 0
      },
      {
        "rating": 5.0,
        "title": "Great Walking Shoe!",
        "text": "I got these for at home. I like wearing shoes inside. So they need to be clean. I got these, and they are comfy and see like they will last a long time. They should, if I only wear them in my house.",
        "verified": true,
        "helpful_votes": 0
      },
      {
        "rating": 5.0,
        "title": "Good fit in a large size",
        "text": "I bought these shoes as a gift for my 25 year old son, who wears a size 16. I know from past experience that New Balance provides a good, consistent fit in their large sizes, and this pair did not disappoint. The fit was great and my son liked the color and style.",
        "verified": false,
        "helpful_votes": 0
      }
    ],
    "store": "New Balance",
    "tags": [],
    "price": 59.96,
    "position": 11,
    "page": 2
  },
  {
    "id": "prod_running_shoes_163",
    "parent_asin": "B00DPG6H3K",
    "category": "Running Shoes",
    "title": "New Balance Women's WL574 Stadium Jacket Running Shoe",
    "description": "We stand for something bigger than sneakers. We champion those who are fearlessly driven by their passions. We elevate sport. We do right by people and the planet. Together, we drive meaningful change in communities around the world. We Got Now.\nNew Balance, is dedicated to helping athletes achieve their goals. It's been their mission for more than a century. It's why they don't spend money on celebrity endorsements. They spend it on research and development. It's why they don't design products to fit an image. They design them to fit. New Balance is driven to make the finest shoes for the same reason athletes lace them up: to achieve the very best.",
    "rating": 4.5,
    "review_count": 285,
    "features": [
      "75% Suede, 25% Mesh",
      "Imported",
      "Rubber sole",
      "This is the 574 Core Plus.",
      "Suede/Mesh upper",
      "ENCAP midsole cushioning combines lightweight foam with a durable polyurethane rim to deliver all-day support",
      "Lace closure"
    ],
    "reviews": [
      {
        "rating": 5.0,
        "title": "Five Stars",
        "text": "Look great and are very comfortable",
        "verified": true,
        "helpful_votes": 0
      },
      {
        "rating": 5.0,
        "title": "Good product",
        "text": "Love this pair and love my other ones!! Fit well and perfect for runnng or wearing casually around town !",
        "verified": true,
        "helpful_votes": 0
      }
    ],
    "store": "New Balance",
    "tags": [],
    "price": 99.99,
    "position": 12,
    "page": 2
  },
  {
    "id": "prod_running_shoes_105",
    "parent_asin": "B07RDP32W8",
    "category": "Running Shoes",
    "title": "New Balance Women's Fresh Foam Arishi Trail V1 Trail Running Shoe",
    "description": "Hit the trails in comfort and style with the Fresh Foam Arishi Trail running shoes from New Balance. These comfortable running shoes are built tough with performance features designed to help keep your feet safe and supported. Toe Protect technology helps shield your feet from rocks, roots and debris as you tackle new terrain, and a durable AT Tread dual lug outsole provides versatile traction for both on- and off-road adventures. These trail shoes are crafted with textile and synthetic uppers that feature classic New Balance branding for a fresh, sporty look. No-sew upper construction adds to the sleek fit and feel that you'd expect from these lightweight running shoes. Underfoot, you\u2019re treated to super soft comfort with Fresh Foam midsole technology that is precision-engineered to deliver an ultra-cushioned, lightweight ride. An EVA foam insert adds even more cushioned comfort to help fuel your runs. Wherever your trail takes you, arrive in comfort with these sleek, stylish and supportive running shoes.",
    "rating": 4.2,
    "review_count": 5959,
    "features": [
      "Imported",
      "Rubber sole",
      "Fresh Foam midsole cushioning is precision engineered to deliver an ultra-cushioned, lightweight ride",
      "GORE-TEX waterproof fabric protects feet from wind, rain and water without sacrificing breathability",
      "AT Tread outsole provides versatile traction during both on and off-road activities",
      "Toe Protect technology helps protect feet from rocks, roots and debris",
      "Upper features no-sew construction for a sleek fit and feel"
    ],
    "reviews": [
      {
        "rating": 5.0,
        "title": "Best walking and running shoes.",
        "text": "I live the fit and comfort of these shoes.",
        "verified": true,
        "helpful_votes": 0
      },
      {
        "rating": 2.0,
        "title": "Not wide, runs small.",
        "text": "I ordered 6.5 wide but it was too small and tight, so I had to exchanged it for size 7 wide.  It is still a bit tight so you need to know if you want wide this isn't the one. Runs small.",
        "verified": true,
        "helpful_votes": 0
      },
      {
        "rating": 5.0,
        "title": "Good shoe",
        "text": "Nice",
        "verified": true,
        "helpful_votes": 0
      },
      {
        "rating": 3.0,
        "title": "Odd fit",
        "text": "While fits well the ankle & back are too high & rub uncomfortably.",
        "verified": true,
        "helpful_votes": 0
      },
      {
        "rating": 5.0,
        "title": "Excelente producto",
        "text": "Excelente producto, cumple con las especificaciones y calidad.  Muy buena adquisici\u00f3n.",
        "verified": true,
        "helpful_votes": 0
      }
    ],
    "store": "New Balance",
    "tags": [],
    "price": 90.53,
    "position": 13,
    "page": 2
  },
  {
    "id": "prod_running_shoes_174",
    "parent_asin": "B096LLNTR4",
    "category": "Running Shoes",
    "title": "Saucony Women's Switchback 2 Trail Running Shoe",
    "description": "Dialed to grip and rip trails fast. For trail runners looking to get to their destination fast, The lightweight Switchback 2 is a race-ready machine that delivers more of what you need\u2014long-distance cushioning placed into a nimble, grippy, and dialed-in package.",
    "rating": 4.2,
    "review_count": 150,
    "features": [
      "Synthetic-and-mesh",
      "Rubber sole",
      "Toothy lugs made of PWRTRAC tacky rubber for grip",
      "New pwrrun+ cushioning is 5% lighter for more protection and flexibility",
      "New sock-like construction featuring a side-set boa lacing system"
    ],
    "reviews": [
      {
        "rating": 4.0,
        "title": "Love the idea, needs some redesign",
        "text": "I really want to like this shoe more. I do actually use them a lot but it took nearly half a year to really break them in, and they\u2019re still fairly difficult to slip into, as the opening is not very flexible. The shoe itself is tight enough where the laces don\u2019t even really need to be there, and the toe box is fairly narrow which isn\u2019t very good for running and hiking. My pinky toe often feels wedged by this one part of the design and frequently causes pain. I really REALLY like the idea of this shoe though and it\u2019s still wearable for moderate hikes under 2 hours, I just wish they put more work and testing. It\u2019s probably better for people with thinner, narrower feet. My feet are medium wide and the top part is kind of high.",
        "verified": true,
        "helpful_votes": 4
      },
      {
        "rating": 3.0,
        "title": "Fits just right",
        "text": "I like the way the shoes fit; however, they are more attractive in the picture than on my feet, at least to me.  They are a little pricey too, but all in all, I would recommend them.",
        "verified": true,
        "helpful_votes": 0
      }
    ],
    "store": "Saucony",
    "tags": [],
    "price": 61.34,
    "position": 14,
    "page": 2
  },
  {
    "id": "prod_running_shoes_028",
    "parent_asin": "B098K9XTDN",
    "category": "Running Shoes",
    "title": "Jaqqra Slip On Sneakers for Women Fashion Sneakers Mesh Walking Shoes Slip On Lightweight Breathable Mesh Running Shoes Outdoor",
    "description": "",
    "rating": 1.0,
    "review_count": 1,
    "features": [
      "womens sandals wide width arch support",
      "\u3010ABOUT SHIPPING\u3011Expedited Shipping:3-7 Days. Standard shipping:14-25 Days. Within 24 Hours Shipping Out.",
      "Big Promotion---All Products Save 10% on 1 of every 2 Qualifying items you purchase\ud83d\udc93",
      "platform sneakers for women closure",
      "Fast Shipping---We ususally shipped out your items within 24 hours\ud83d\udc93 and It usually takes 10-18 days for shipping to you\ud83d\udc93and the expedited shipping:3-7 days. \ud83d\udc93Please wait it more patience. Thanks. \ud83d\udc93",
      "summer sandals for women dressy summer sandals for women comfortable white summer sandals for women summer sandals for women 2022 sexy sandals for women black sandals for women sandals for women with arch support sandals for women dressy sandals for women 2022 sandals for women with arch support walking sandals for women with arch support and comfort sandals for women with arch support sandals for women with arch support and back strap",
      "closed toe wedges for women black closed toe wedges for women closed toe wedges for women dressy white closed toe wedges for women closed toe wedges for women wide width closed toe wedges for women sexy closed toe wedges for women comfort closed toe wedges for women sandals closed toe wedges for women 2022 white wedges for women white wedges for women wedding black and white wedges for women white wedges for women sandals white wedges for women closed toe wedges for women dressy summer",
      "gladiator sandals for women, summer casual flats sandals open toe post back zipper vintage bohemian roman shoes sandals for women flat,casual summer beach sandals slip-on flip flop open toe roman gladiator sandals travel shoes summer sandals for women comfort platform leather sandals floral embroidery casual summer open-toe sandals dressy travel beach non-slip slippers women sandals sandals for women dressy summer boho flower lace flat sandals open toe casual beach sandals comfy roman shoes",
      "sandals for women dressy rhinestone flip flop sandals strappy open toe slippers casual summer beach crystal shoes sandals for women fashion t-strap clip toe gladiator sandals roman shoes casual summer beach flip flops sandals sandals for women,womens studded flat sandals wedge sandals casual summer beach sandals flip flops sparkly shoes sandals for women dressy 2022 fish mouth flat wedge strappy sandals open toe summer beach sandals espadrille platform",
      "t strap sandals for women dressy summer flat boho sandals open toe roman shoes casual beach flip flop sandals sandals for women leopard flat sandals open toe flip flop sandals casual summer beach sandals comfy roman shoes sandals for women dressy wedge crystal sparkly boho sandals open toe casual summer beach sandals roman shoes sandals for women bowknot espadrille platform wedge sandals slip-on open toe casual beach sandals flat slippers"
    ],
    "reviews": [
      {
        "rating": 1.0,
        "title": "Sole is just a non flexible plastic",
        "text": "Don\u2019t even look at this lol",
        "verified": true,
        "helpful_votes": 1
      }
    ],
    "store": "Jaqqra",
    "tags": [],
    "price": 3.85,
    "position": 15,
    "page": 2
  },
  {
    "id": "prod_running_shoes_083",
    "parent_asin": "B0969FM5Q9",
    "category": "Running Shoes",
    "title": "New Balance Kid's 519 V2 Alternative Closure Running Shoe",
    "description": "The New Balance 519v2 kids' performance shoe is made with a versatile upper and a signature REVlite midsole to form a classic shoe that's comfortable, durable and pairs effortlessly with all of your kid's go-to gear. This pair of running shoes for kids is designed with no-sew overlays to help ensure a top-notch fit and a sleek feel that's perfect for all-day, any-day wear. The synthetic and mesh construction offers breathability and a proper fit, so your little one can tackle whatever their day throws at them, from recess shenanigans with friends to after-school practice. Best of all is the cool style of these cushioned running shoes for kids. Fun, playful colors and eye-catching patterns make for a pair of sneakers that fashion-conscious youngsters will love.",
    "rating": 4.7,
    "review_count": 1606,
    "features": [
      "50% Synthetic, 50% Mesh",
      "Imported",
      "Rubber sole",
      "Comfortable Kids' Running Shoes: Thanks to the REVlite midsole, which delivers incredibly lightweight cushioning, these kids' running shoes easily go from the classroom to the playground and beyond",
      "Great Fit: Designed with no-sew overlays to ensure a sleek fit and incredible feel, these kids' performance shoes will be a joy to wear for your active little one",
      "Breathable Comfort: The synthetic and mesh uppers on these New Balance kids' running shoes create amazing breathability, helping to keep their feet comfortable when the pace picks up",
      "Incredible Support: With a strong and durable rubber outsole, these kids' shoes provide impressive support and can stand up to daily wear-and-tear, no matter what your child gets up to",
      "Fun, Kid-Friendly Design: These shoes are designed for kids first, with playful colors, patterns and fun designs they're sure to love whether they're headed to school, practice or the park"
    ],
    "reviews": [
      {
        "rating": 5.0,
        "title": "MY new blue shoes!",
        "text": "My toddler LOVES his new blue shoes! These replaced a very beloved and very worn-out pair of shoes that I needed him to finally let go of. These are so bright and fun, he loves running around and showing them to everyone. My kid is a 5.5 per the foot measuring tool we have and these seem to fit just right. He\u2019s so proud of these new shoes! I also love that they weren\u2019t stupidly expensive.",
        "verified": true,
        "helpful_votes": 3
      },
      {
        "rating": 2.0,
        "title": "Very narrow",
        "text": "Way too small for my 3 year old \u2639\ufe0f",
        "verified": true,
        "helpful_votes": 0
      },
      {
        "rating": 5.0,
        "title": "Great product",
        "text": "As described and quick delivery",
        "verified": true,
        "helpful_votes": 0
      },
      {
        "rating": 5.0,
        "title": "They were perfect",
        "text": "First walking shoes.",
        "verified": true,
        "helpful_votes": 0
      },
      {
        "rating": 5.0,
        "title": "Looks better in person",
        "text": "This sneakers look awesome on my daughter and my son got the blue ones",
        "verified": true,
        "helpful_votes": 0
      }
    ],
    "store": "New Balance",
    "tags": [],
    "price": 20.0,
    "position": 16,
    "page": 2
  },
  {
    "id": "prod_running_shoes_059",
    "parent_asin": "B08CHWZRCD",
    "category": "Running Shoes",
    "title": "Brooks Womens Glycerin 18 Running Shoe",
    "description": "A bit like running in the clouds. Thanks to the increased elasticity of the upper and the super-soft cushioning throughout the length, these men's running shoes are the ultimate comfort. Super soft cushioning. The revised ratio between midsole and outer sole allows you to increase LOFT DNA to achieve even more extreme softness at the sole of the foot, without losing reactivity or endurance. An OrthoLiteTM insole ensures an extraordinary wearing comfort.",
    "rating": 4.7,
    "review_count": 6787,
    "features": [
      "Imported",
      "Rubber sole",
      "THIS WOMEN'S SHOE IS FOR: The Glycerin 18 is perfect for runners who think there's no such thing as too much cushioning. The upper enhances comfort by perfectly balancing stretch and structure.",
      "SUPPORT AND CUSHION: Provides neutral support while offering the maximum amount of cushioning. Ideal for road running, cross training, the gym or wherever you might want to take them! Predecessor: Glycerin 17.",
      "SUPER-SOFT CUSHIONING: Increased DNA LOFT super-soft cushioning allows for even more extreme softness, without losing responsiveness or durability, while the OrthoLite sockliner provides premium step-in comfort.",
      "PLUSH FIT: The plush feel of an internal stretch bootie surrounds your foot and moves and expands with your stride. The engineered mesh upper enhances the fit.",
      "SMOOTH TRANSITIONS: The plush transition zone makes every move from heel to toe feel incredibly soft and smooth."
    ],
    "reviews": [
      {
        "rating": 1.0,
        "title": "Defective manufacturing",
        "text": "I\u2019m this was my second pair of these shoes within 6 months but this pair is very u comfortable on the left shoe and I can\u2019t do walks in them.  Very disappointed in it... it\u2019s like the left shoe has a defect I it.  Unfortunately I saved the shoe for over a month before I wore it and too late to return.",
        "verified": true,
        "helpful_votes": 0
      },
      {
        "rating": 5.0,
        "title": "Great support",
        "text": "These are very comfortable and supportive. I started wearing Brooks when I got planter fasciitis. I haven\u2019t had issues in a long time. I tried another model, but I went back to these.",
        "verified": true,
        "helpful_votes": 0
      },
      {
        "rating": 5.0,
        "title": "My Shoe!",
        "text": "These are the only shoes I have been wearing on a daily basis for over 10 years, Brooks Glycerin. My feet have seen many years of 12 hour shifts and are in sad shape. I have a dress pair, a pair I wear indoors, and several pairs for outdoors and yard work.  I can wear a man's 8 1/2 D or a Women's 9 1/2 wide and they fit perfectly.  If you need a cushioned shoe with good support these are the ones to buy.",
        "verified": true,
        "helpful_votes": 0
      },
      {
        "rating": 1.0,
        "title": "Don't Buy!!",
        "text": "The shoes are NOT worth 130.00 or 50.00 inserts last less than one month shoes themselves no arch support. In the end caused my feet problems.",
        "verified": true,
        "helpful_votes": 0
      },
      {
        "rating": 4.0,
        "title": "Comfortable Shoe",
        "text": "Comfortable shoe however shoes is not black it is a very dark grey with some black trimming.",
        "verified": true,
        "helpful_votes": 0
      }
    ],
    "store": "Brooks",
    "tags": [],
    "price": 160.39,
    "position": 17,
    "page": 2
  },
  {
    "id": "prod_running_shoes_168",
    "parent_asin": "B08TBD9Q9D",
    "category": "Running Shoes",
    "title": "DREAM PAIRS Boys Girls Running Shoes Athletic Sneakers",
    "description": "",
    "rating": 4.5,
    "review_count": 2717,
    "features": [
      "synthetic sole",
      "Highly-breathable fabric knit upper offers dependable comfort.",
      "Elasticized laces with hook-and-loop strap, and Padded tongue and collar.",
      "Mesh lining and cushioned foam footbed for a great in-shoe feel.",
      "Breathable and cushioned sock liner keeps feet odor-free and dry.",
      "Lightweight molded EVA midsole provides extra comfort and cushion."
    ],
    "reviews": [
      {
        "rating": 5.0,
        "title": "Daughter Loves them",
        "text": "These have been great shoes. We got them at Christmas time and she has loved them. They have been pretty durable since she wears them even in the snow. They are easy to put on and easy to take off. She has no complaints and neither do I.",
        "verified": true,
        "helpful_votes": 1
      },
      {
        "rating": 2.0,
        "title": "They don\u2019t hold up well",
        "text": "They barely made it 3 months. Started falling apart almost immediately. Order something else",
        "verified": true,
        "helpful_votes": 0
      },
      {
        "rating": 5.0,
        "title": "Boys shoe",
        "text": "Grandson needed new pair of shoes he picked the red/black very nice shoe. That fits as expected.",
        "verified": true,
        "helpful_votes": 0
      },
      {
        "rating": 4.0,
        "title": "Seems good quality. Fit was a bit small.",
        "text": "Seems good quality. Fit was a bit small.",
        "verified": true,
        "helpful_votes": 0
      },
      {
        "rating": 5.0,
        "title": "Great Grandkids gifts",
        "text": "Their favorite color",
        "verified": false,
        "helpful_votes": 0
      }
    ],
    "store": "DREAM PAIRS",
    "tags": [],
    "price": 25.99,
    "position": 18,
    "page": 2
  },
  {
    "id": "prod_running_shoes_093",
    "parent_asin": "B09CLKTT2N",
    "category": "Running Shoes",
    "title": "ASICS Men's GlideRide 3 Running Shoes",
    "description": "",
    "rating": 4.3,
    "review_count": 32,
    "features": [
      "100% Synthetic",
      "Rubber sole",
      "3D print details: Strategically positioned throughout the upper to improve stability",
      "Jacquard mesh upper: Creates a softer feel against the foot while improving breathability",
      "GUIDESOLE Technology: The curved sole design and stiff forefoot of our GUIDESOLE technology reduce ankle flexion and provide a shock-absorbent landing zone to lessen fatigue of other leg muscles and increase runner efficiency.",
      "FF BLAST cushioning: Creates a softer feeling at foostrike and a more responsive rebound",
      "FLYTEFOAM Propel Technology: ASICS energetic foam formulation that provides supreme bounce thanks to a unique elastomer compound."
    ],
    "reviews": [
      {
        "rating": 3.0,
        "title": "Significantly smaller fit than GR2",
        "text": "I don't understand how the fit can be so different between generations, but it's just too small.  The outside dimensions look the same, but what looks like happened is the new foam is encroaching on the upper and there's just not enough room for your foot in there.  Returned.  Sad, because I liked the Glideride 2 and expected a better shoe, and a similar fitting shoe.",
        "verified": false,
        "helpful_votes": 1
      }
    ],
    "store": "ASICS",
    "tags": [],
    "price": 149.95,
    "position": 19,
    "page": 2
  },
  {
    "id": "prod_running_shoes_152",
    "parent_asin": "B07WZGQ7CM",
    "category": "Running Shoes",
    "title": "WONESION Mens Breathable Walking Tennis Running Shoes Blade Fashion Sneakers",
    "description": "",
    "rating": 4.2,
    "review_count": 20698,
    "features": [
      "Rubber sole",
      "UPPER---Fashion mesh upper, soft and breathable. Super breathable upper keeps your feet clean and cool.",
      "INSOLES---The interior of the shoe uses a honeycomb insole that adds cushioning and impact resistance to provide a comfortable feeling for your feet.",
      "OUTSOLES---Blade soles, made of TPU rubber, durable and enhanced non-slip design and make you walk and sports freely on all kinds of ground.",
      "OCCASIONS---Perfect choice for many occasion: Running, training, gym, casual walking, workout, traveling, hiking, camping, climbing, outdoor activities and daily wear.",
      "Stylish color scheme gives you a different visual experience, slip-on closure type easy put on & off. Simple style, all-match colors, can be match any clothing."
    ],
    "reviews": [
      {
        "rating": 4.0,
        "title": "Waited a year of use before my review",
        "text": "To be honest I only bought these shoes from the way they looked (Camo) and only after watching a few viedeos on them.. the price is great.. the comfort is surprising and easy to wear. I weith right at 300 lbs and they support me just fine.. now know I also own Brooks, NB, Adidas, UA HOVR, etc... shoes as well.. are these as comfortable as they are.. No.. but they sure pack a punch bang for the buck thought.. NOW.. One huge issue.;. and again I wanted to wait and see if the soles \"scuffed up: for traction.. but no.. If there is rain.. and the water on any surface is thin.. like tile, ocncrete, wood or anything besices most asphalt.. this shoe is like your walking on thin ice.. and YOU WILL SKID! Be warned.. Good.. but Dry use ONLY",
        "verified": true,
        "helpful_votes": 14
      },
      {
        "rating": 2.0,
        "title": "Uncomfortable",
        "text": "Order larger since these run real small.",
        "verified": true,
        "helpful_votes": 0
      },
      {
        "rating": 5.0,
        "title": "Est\u00e1n dura buen estilo  me gustaron mucho",
        "text": "Gracias me gusta mucho",
        "verified": true,
        "helpful_votes": 0
      },
      {
        "rating": 4.0,
        "title": "Oddly they're a nice shoe",
        "text": "I didn't expect much from these but, they're surprisingly comfortable. They're true to size and the color is pretty neon. The strap around the back is awkward however and I will likely cut it off so it doesn't catch on something when I'm walking. The \"just so so\" text on the shoe makes no sense... Haha it could easily have been left off... But, again... They're different and bright.",
        "verified": true,
        "helpful_votes": 0
      },
      {
        "rating": 5.0,
        "title": "Love these shoes",
        "text": "My feet haven't felt this good in years",
        "verified": true,
        "helpful_votes": 0
      }
    ],
    "store": "WONESION",
    "tags": [],
    "price": 45.99,
    "position": 20,
    "page": 2
  },
  {
    "id": "prod_running_shoes_115",
    "parent_asin": "B07DCT4HTL",
    "category": "Running Shoes",
    "title": "adidas Originals Unisex-Child Swift Running Shoe",
    "description": "adidas authentic shoes",
    "rating": 4.7,
    "review_count": 4339,
    "features": [
      "100% Rubber",
      "Rubber sole",
      "Snug fit",
      "OrthoLite sockliner",
      "Lightweight shoes"
    ],
    "reviews": [
      {
        "rating": 5.0,
        "title": "Five Stars",
        "text": "Love it",
        "verified": true,
        "helpful_votes": 1
      },
      {
        "rating": 5.0,
        "title": "I love them",
        "text": "They feel like you have nothing on I love it",
        "verified": true,
        "helpful_votes": 0
      },
      {
        "rating": 5.0,
        "title": "Great baby shoe!",
        "text": "Great baby shoe!",
        "verified": true,
        "helpful_votes": 0
      },
      {
        "rating": 5.0,
        "title": "Great looking shoe",
        "text": "Bought it for my son.  He love it.  Fit true to size",
        "verified": true,
        "helpful_votes": 0
      },
      {
        "rating": 5.0,
        "title": "Great shoes",
        "text": "Love these shoes for my toddler. They fit great, always look clean, and are easily washed. They do, however, tie and not velcro. They still look great after several months of everyday wear.",
        "verified": true,
        "helpful_votes": 0
      }
    ],
    "store": "adidas Originals",
    "tags": [
      "Sponsored"
    ],
    "price": 37.29,
    "position": 21,
    "page": 3
  },
  {
    "id": "prod_running_shoes_099",
    "parent_asin": "B0844MLRFB",
    "category": "Running Shoes",
    "title": "Xero Shoes Men's HFS Running Shoes - Zero Drop, Lightweight & Barefoot Feel",
    "description": "",
    "rating": 4.5,
    "review_count": 1129,
    "features": [
      "A NEW LIGHTWEIGHT road running shoe. Foot-shaped for comfort. Built for speed!",
      "Made in the USA or Imported",
      "GRIP + COMFORT - Flexible to support natural foot motion, and grippy with its tire tread-inspired FeelTrue rubber sole",
      "SHAPED FOR COMFORT, BUILT FOR SPEED - Xero HFS features a lightweight, minimalist build that contours to the shape of your feet. Its spacious toe-box allows you to splay, spread, and relax your toes for superior comfort",
      "XERO DROP SOLE FOR PERFECT POSTURE - The Xero Drop sole offers a non-elevated heel and is low-to-the-ground - this allows for proper posture, balance, and agility for all-round performance",
      "FLEX YOUR FEET, FEEL THE FLOOR - Our tire tread inspired patented 5.5mm FeelTrue sole strikes a balance between just-right protection and feedback - it delivers heel to toe cues to the brain for your best run ever. Allows your feet to bend and flex as nature intended",
      "TRAVEL FRIENDLY, 5000 MILE WARRANTY - Xero HFS\u2019 extra-durable construction is backed by our 5,000 Mile Feel the World Sole Promise. Being ultra-flexible, you can roll \u2018em up and put in your pack or pocket for compact storage and easy travel",
      "VEGAN FRIENDLY - Xero Shoes believes in promoting healthy and sustainable lifestyles which is why the HFS is made with zero animal products"
    ],
    "reviews": [
      {
        "rating": 5.0,
        "title": "Surpassed My Expectations",
        "text": "I feel like now I can write an honest review. I have run for years, 3 5k per week. My go to shoes were NB or Brooks and I loved them. Started seeing Xero Shoes pop up on social media and YouTube. I looked them for months and it seemed like a gimmick product. After some time I said ok I am going to try this shoe and see if they meet their hype. In July of this year I ordered the Prio Cross Trainer model. Now their instructions said adjust over a couple of weeks. Well I said hell no and put them to the test right out of the box. I wore them every chance I got for 30 days straight. I found them comfortable right out of the box and I did not experience any foot or leg discomfort during the break period. I began liking them the more I wore them. At day 31 I put my Brooks Adrenaline runners on. Within 15 mins I was aware of how unbalanced I was in that shoe and while walking around in my home said, I can\u2019t wear these any more I have to put my Xero Shoes on. I swear I referred to them specifically. I have since purchased 2 pairs of the HFS model runners and they are my favorite shoe. I wear them every day. In my old shoes at the end of the day I would change to my slides, I literally have these on until I go to bed. Closest thing to walking barefoot and still having a shoe on.",
        "verified": true,
        "helpful_votes": 7
      },
      {
        "rating": 5.0,
        "title": "If you like barefoot shoes give these a try.",
        "text": "I wear a size 11 in most running shoes. Ordered a 10 1/2 in this and it fits great. My feet are on wider side so shorter sizes work for me if the shoe is somewhat wide. Really comfortable and appears well made. I look forward to trying other models. Unlike many other barefoot manufacturers I didn\u2019t see any irregularities in how the shoe was put together.",
        "verified": true,
        "helpful_votes": 2
      },
      {
        "rating": 5.0,
        "title": "Comfortable as \"bare foot\" shoes",
        "text": "I have purchased 2 Xero Men's HFS Running Shoes - Zero Drop and I have been very happy and comfortable wearing them. I've successfully walked and run with them when I visited Philippines for a month and have gotten used to the \"bare foot\" concept. Although I'm still comfortable wearing my Adidas running shoes, I found myself to be wearing my bare foot shoes more often now as I really find them much lighter, comfortable (for bare foot shoes) and lighter/easier to pack on day or extended trips. I've only been wearing them for the last 2 months or so, so long term I would still need to see how they stand up.",
        "verified": true,
        "helpful_votes": 1
      },
      {
        "rating": 5.0,
        "title": "Forms to feet",
        "text": "Really nice lightweight shoes that forms to feet rather than walking with slight incline on heel. One of the best work out shoes there are. Not for running or basket ball- in my opinion, though more for stretching, walking,  calisthenics, boxing or light aerobics.",
        "verified": true,
        "helpful_votes": 0
      },
      {
        "rating": 3.0,
        "title": "Crazy not as comfortable as NEw BaLanCe Minimus",
        "text": "The sole needs a bit more cushion.",
        "verified": true,
        "helpful_votes": 0
      }
    ],
    "store": "Xero Shoes",
    "tags": [],
    "price": 124.99,
    "position": 22,
    "page": 3
  },
  {
    "id": "prod_running_shoes_061",
    "parent_asin": "B00Q4V24RQ",
    "category": "Running Shoes",
    "title": "ASICS Women's Gel-Venture 5 Running Shoes",
    "description": "The GEL-Venture 5 provides great fit and everyday comfort, with Rearfoot GEL Cushioning System and a rugged outsole ideal for a variety of terrains.\nIn 1949, Mr. Kihachiro Onitsuka began his athletic footwear company (Onitsuka Co., Ltd.) by manufacturing basketball shoes out of his living room in Kobe, Japan. He chose the name ASICS for his company in 1977, based on a famous Latin phrase \"Anima Sana In Corpore Sano,\" which, when translated, expresses the ancient ideal of \"A Sound Mind in a Sound Body.\" Taking the acronym of this phrase, ASICS was founded on the belief that the best way to create a healthy and happy lifestyle is to promote total health and fitness. Today, ASICS offers a full line of performance-driven athletic shoes and technical active sports apparel and accessories dedicated to bringing harmony to the body and soul.",
    "rating": 4.5,
    "review_count": 22884,
    "features": [
      "100% Synthetic",
      "Imported",
      "Rubber sole",
      "Rearfoot GEL Cushioning System: Attenuates shock during impact phase and allows for a smooth transition to midstance.",
      "Removable Sockliner: A sockliner which can be removed to accommodate a medical orthotic.",
      "Trail Specific Outsole: Reversed lugs provide uphill and downhill traction on all types of terrain.",
      "AHAR Outsole: Acronym for ASICS High Abrasion Rubber. Placed in critical areas of the outsole for exceptional durability."
    ],
    "reviews": [
      {
        "rating": 5.0,
        "title": "Great shoe!",
        "text": "Ordering shoes online sometimes is hard, because you're not sure what you will get.  I have ordered Asics many times and I have never been disappointed.  The fit is just right and you can't beat the quality.  These are keepers for sure.",
        "verified": true,
        "helpful_votes": 1
      },
      {
        "rating": 5.0,
        "title": "FOREVER SHOES",
        "text": "Yeah, I\u2019ve boughten these twice now. Hehehehehe",
        "verified": true,
        "helpful_votes": 0
      },
      {
        "rating": 5.0,
        "title": "Five Stars",
        "text": "Bought these for my daughter. Finally, a shoe she will wear properly and often. Well done.",
        "verified": true,
        "helpful_votes": 0
      },
      {
        "rating": 5.0,
        "title": "The fit was spot on",
        "text": "I like the colors. The fit was good. I would buy them again.<br />Susan Mejia",
        "verified": true,
        "helpful_votes": 0
      },
      {
        "rating": 5.0,
        "title": "Comfy and Cute!",
        "text": "Comfy and cute! I really like these shoes and would recommend them!",
        "verified": true,
        "helpful_votes": 0
      }
    ],
    "store": "ASICS",
    "tags": [],
    "price": 57.95,
    "position": 23,
    "page": 3
  },
  {
    "id": "prod_running_shoes_110",
    "parent_asin": "B07DWMD434",
    "category": "Running Shoes",
    "title": "Brooks Womens Ghost 11 Running Shoe",
    "description": "The balanced cushioning helps to offer a smooth ride to the neutral runners looking for a versatile performance. With the new soft interior and a refined mesh upper, practically vanishes on the foot mainly thanks to the strategic position of stretch and Structure. Crash Pad segmented along the entire length of the foot that sustains the foot every time it touches the ground and offers soft transitions and the BioMoGo DNA and DNA Loft cushioning even more assure every step of the foot.",
    "rating": 3.8,
    "review_count": 8,
    "features": [
      "mesh lining",
      "Lace-Up closure",
      "Machine Wash",
      "SHOE SIZE: \"B\" = Medium width, \"D\" = Wide width",
      "FOOT SUPPORT: Ideal for runners with a medium to high arch looking for neutral support.",
      "BALANCED, SOFT CUSHIONING: BioMoGo DNA and DNA LOFT cushioning work together to provide a just-right softness underfoot without losing responsiveness and durability\u2014yet it feels lighter than ever.",
      "SMOOTH, STABLE RIDE: The Segmented Crash Pad is designed to adapt to each foot fall, so no matter how your foot lands, you\u2019ll enjoy the smoothest ride possible.",
      "SOFT, SECURE FIT: The newly engineered mesh upper practically disappears on foot with strategically placed stretch and structure where you need it most."
    ],
    "reviews": [
      {
        "rating": 5.0,
        "title": "Perfect pair of Running shoes",
        "text": "I\u2019ve been wearing Brooks running shoes for about 4 years now and they do not disappoint. At first I thought the Ghost 11 would take some time to break in unlike my other Brooks running shoes. This was not the case as by day 2 they felt very comfortable. I will continue to wear Brooks running shoes. I am a fan. I\u2019ve even convinced my husband to switch from New Balance to Brooks and he did.",
        "verified": true,
        "helpful_votes": 2
      },
      {
        "rating": 5.0,
        "title": "Brooks are the best!!",
        "text": "Just love Brooks tennis shoes. This pair is probably my 4th or 5th pair from Brooks and I won't buy any other brand at this point they are so comfortable. Love the colors!!! Super fast shipping!!",
        "verified": true,
        "helpful_votes": 1
      },
      {
        "rating": 5.0,
        "title": "Perfect for the gym.",
        "text": "I use these for the gym and love them.",
        "verified": true,
        "helpful_votes": 0
      },
      {
        "rating": 5.0,
        "title": "Worth every cent!",
        "text": "Brooks always has the best shoes! These are dupe cute looking and wonderful for running/working out",
        "verified": true,
        "helpful_votes": 0
      },
      {
        "rating": 5.0,
        "title": "Love running in Brooks!",
        "text": "I have been wearing brooks to run in for several years and just happened upon these at Amazon! Came quickly and perfect!",
        "verified": true,
        "helpful_votes": 0
      }
    ],
    "store": "Brooks",
    "tags": [],
    "price": 119.99,
    "position": 24,
    "page": 3
  },
  {
    "id": "prod_running_shoes_169",
    "parent_asin": "B07DNG6GYQ",
    "category": "Running Shoes",
    "title": "ASICS Women's Gel-Kenun Lyte MX Running Shoes",
    "description": "Cloud-like comfort meets street-forward style in the ultra-lightweight GEL-Kenun Lyte MX. Fusing the fluid lines of the GEL-Kenun series with seat-belt buckle design inspiration, this cushioned silhouette delivers a secure, supportive fit that works with your natural gait to guide efficient strides all day long. Borrowing from the iconic GEL-LYTE III, a split tongue and plush collar make for an easy-on, easy-off trait that doubles as a style-focused detail. Weight: 6.4. Heel Height: 22. Forefoot Height: 12.",
    "rating": 4.4,
    "review_count": 63,
    "features": [
      "Synthetic-and-mesh",
      "Rubber sole"
    ],
    "reviews": [
      {
        "rating": 3.0,
        "title": "Okay for casual, not a whole lot of support though",
        "text": "Cute shoe but not ideal for being on your feet for hours. I work 12 hour shifts and my heels were killing me the first 12 hour shift I worked in them. If comfort and stability is what you\u2019re going for, I\u2019d go with a different ASICS shoe. I wouldn\u2019t ever run in them and I\u2019m looking for inserts/a new work shoe but I\u2019ll still wear them casually",
        "verified": true,
        "helpful_votes": 0
      }
    ],
    "store": "ASICS",
    "tags": [],
    "price": 64.9,
    "position": 25,
    "page": 3
  }
]